supersynthetic_data_generator/__init__.py
supersynthetic_data_generator/supersynthetic_data_generator.py
supersynthetic_data_generator-0.1.3.dist-info/LICENSE.lic
supersynthetic_data_generator-0.1.3.dist-info/METADATA
supersynthetic_data_generator-0.1.3.dist-info/WHEEL
supersynthetic_data_generator-0.1.3.dist-info/top_level.txt
supersynthetic_data_generator-0.1.3.dist-info/RECORD
