Metadata-Version: 2.1
Name: supersynthetic-data-generator
Version: 0.1.3
Summary: A library to generate synthetic datasets for testing ML models
Home-page: https://github.com/UjwalWtg/supersynthetic-data-generator
Author: Ujwal Watgule
Author-email: ujwalwatgule@gmail.com
Classifier: Programming Language :: Python :: 3
Classifier: License :: OSI Approved :: MIT License
Classifier: Operating System :: OS Independent
Requires-Python: >=3.6
License-File: LICENSE.lic
Requires-Dist: numpy
Requires-Dist: pandas
Requires-Dist: faker
